cpython_near_wasm_opt/__init__.py
cpython_near_wasm_opt/__main__.py
cpython_near_wasm_opt/cli.py
cpython_near_wasm_opt/core.py
cpython_near_wasm_opt/defaults.py
cpython_near_wasm_opt/bin/wasm-as
cpython_near_wasm_opt/bin/wasm-dis
cpython_near_wasm_opt/bin/wasm-opt
cpython_near_wasm_opt/lib/libbinaryen.dylib
cpython_near_wasm_opt/lib/python-stdlib.zip
cpython_near_wasm_opt/lib/python.wasm
cpython_near_wasm_opt-0.8.13.dist-info/licenses/LICENSE
cpython_near_wasm_opt-0.8.13.dist-info/METADATA
cpython_near_wasm_opt-0.8.13.dist-info/WHEEL
cpython_near_wasm_opt-0.8.13.dist-info/entry_points.txt
cpython_near_wasm_opt-0.8.13.dist-info/top_level.txt
cpython_near_wasm_opt-0.8.13.dist-info/RECORD
