Metadata-Version: 2.4
Name: cpython-near-wasm-opt
Version: 0.8.13
Summary: CPython-NEAR WASM optimizer tool
Project-URL: Homepage, https://github.com/past-hypothesis/cpython-near-wasm-opt
Project-URL: Bug Tracker, https://github.com/past-hypothesis/cpython-near-wasm-opt/issues
Requires-Python: >=3.9
License-File: LICENSE
Requires-Dist: wasmtime
Requires-Dist: lz4
Dynamic: license-file
